deeptechv_ai/__init__.py
deeptechv_ai/__main__.py
deeptechv_ai/client.py
deeptechv_ai-0.2.0.dist-info/LICENCE
deeptechv_ai-0.2.0.dist-info/METADATA
deeptechv_ai-0.2.0.dist-info/WHEEL
deeptechv_ai-0.2.0.dist-info/entry_points.txt
deeptechv_ai-0.2.0.dist-info/top_level.txt
deeptechv_ai-0.2.0.dist-info/RECORD
