Metadata-Version: 2.1
Name: deeptechv_ai
Version: 0.2.0
Summary: Techvantage AI Developer Toolkit for Deepseek
Author: Techvantage
Classifier: Programming Language :: Python :: 3
Classifier: License :: OSI Approved :: MIT License
Classifier: Operating System :: OS Independent
Requires-Python: >=3.6
License-File: LICENCE
Requires-Dist: openai
Requires-Dist: requests
